README.md
setup.cfg
setup.py
TOPSIS_Eknoor_101803169/Eknoor_kaur_101803169_assignment6.py
TOPSIS_Eknoor_101803169.egg-info/PKG-INFO
TOPSIS_Eknoor_101803169.egg-info/SOURCES.txt
TOPSIS_Eknoor_101803169.egg-info/dependency_links.txt
TOPSIS_Eknoor_101803169.egg-info/entry_points.txt
TOPSIS_Eknoor_101803169.egg-info/requires.txt
TOPSIS_Eknoor_101803169.egg-info/top_level.txt