Metadata-Version: 2.1
Name: TOPSIS-Eknoor-101803169
Version: 1.1.2
Summary: A Python package for topsis analysis.
Home-page: UNKNOWN
Author: Eknoor Kaur
Author-email: eknoorbehla78677@gmail.com
License: MIT
Platform: UNKNOWN
Classifier: License :: OSI Approved :: MIT License
Classifier: Programming Language :: Python :: 3
Classifier: Programming Language :: Python :: 3.7
